pcap_to_ditg/__init__.py
pcap_to_ditg/pcap_to_ditg.py
pcap_to_ditg/util.py
pcap_to_ditg-1.0.1.dist-info/METADATA
pcap_to_ditg-1.0.1.dist-info/RECORD
pcap_to_ditg-1.0.1.dist-info/WHEEL
pcap_to_ditg-1.0.1.dist-info/top_level.txt
