Metadata-Version: 2.1
Name: pcap-to-ditg
Version: 1.0.1
Summary: Generate DITG script files from a pcap file
Home-page: http://github.com/devenbansod/pcap_to_DITG
Author: Deven Bansod
Author-email: devenbansod.bits@gmail.com
License: LICENSE
Platform: UNKNOWN
Classifier: License :: OSI Approved :: MIT License
Classifier: Operating System :: OS Independent
Requires-Dist: dpkt
